factowl/__init__.py
factowl/abstain_detection.py
factowl/atomic_facts_sped_up_vllm.py
factowl/clm_vllm.py
factowl/download_data.py
factowl/factscorer_sped_up_vllm.py
factowl/io.py
factowl/lm.py
factowl/npm.py
factowl/openai_lm.py
factowl/retrieval.py
factowl/retrieval_db.py
factowl/utils.py
factowl/visualization/__init__.py
factowl/visualization/draw_predictions.py
factowl-0.2.2.dist-info/licenses/LICENSE
factowl-0.2.2.dist-info/METADATA
factowl-0.2.2.dist-info/WHEEL
factowl-0.2.2.dist-info/top_level.txt
factowl-0.2.2.dist-info/RECORD
