Metadata-Version: 2.4
Name: factowl
Version: 0.2.2
Summary: Tools for fact extraction, scoring and LLM evaluation (FactOwl)
Author-email: Andrey Sakhovsky and Nikita Sushko and Skoltech NLP Lab <sushko@airi.net>
License: MIT License
Project-URL: Homepage, https://github.com/s-nlp/factowl
Project-URL: Documentation, https://github.com/s-nlp/factowl#readme
Project-URL: Source, https://github.com/s-nlp/factowl
Project-URL: Issues, https://github.com/s-nlp/factowl/issues
Requires-Python: >=3.9
License-File: LICENSE
Requires-Dist: nltk==3.9.1
Requires-Dist: openai==1.88.0
Requires-Dist: pandas==2.3.0
Requires-Dist: python-dateutil==2.9.0.post0
Requires-Dist: pytz==2025.2
Requires-Dist: sentence-transformers==4.1.0
Requires-Dist: spacy-legacy==3.0.12
Requires-Dist: spacy-loggers==1.0.5
Requires-Dist: spacy==3.8.7
Requires-Dist: transformers==4.52.4
Requires-Dist: vllm==0.9.1
Requires-Dist: wikipedia==1.4.0
Requires-Dist: rank-bm25==0.2.2
Dynamic: license-file
